{"swagger":"2.0","info":{"version":"2.0.0","title":"Runestake Server","description":"Project","termsOfService":"http://swagger.io/terms/","contact":{"name":"Chicmic Team"},"license":{"name":"MIT"}},"paths":{"/v1/serverResponse":{"get":{"tags":["User"],"summary":"Route to get server response (Is server working fine or not?).","responses":{"200":{"description":"success"}},"parameters":[],"security":[]}},"/v1/user/register":{"post":{"tags":["User"],"summary":"Route to register a new user.","responses":{"200":{"description":"success"}},"parameters":[{"in":"body","name":"body","schema":{"$ref":"#/definitions/Register"}}],"security":[]}},"/v1/user/login":{"post":{"tags":["User"],"summary":"Route to login a user.","responses":{"200":{"description":"success"}},"parameters":[{"in":"body","name":"body","schema":{"$ref":"#/definitions/Login"}}],"security":[]}},"/v1/user/update-user":{"put":{"tags":["User"],"summary":"Route to update a user.","responses":{"200":{"description":"success"}},"parameters":[{"in":"body","name":"body","schema":{"$ref":"#/definitions/UpdateUser"}}],"security":[{"userTokenHeader":[]}]}},"/v1/user/get-user":{"get":{"tags":["User"],"summary":"Route to get a user.","responses":{"200":{"description":"success"}},"parameters":[],"security":[{"userTokenHeader":[]}]}}},"definitions":{"Register":{"type":"object","properties":{"email":{"type":"string","format":"email","description":"User's email."},"password":{"type":"string","description":"User's password."}},"required":["email","password"],"additionalProperties":false},"Login":{"type":"object","properties":{"email":{"type":"string","format":"email","description":"User's email."},"password":{"type":"string","description":"User's password."}},"required":["email","password"],"additionalProperties":false},"UpdateUser":{"type":"object","properties":{},"additionalProperties":false}},"schemes":["http","https"],"consumes":["application/json"],"produces":["application/json"],"securityDefinitions":{"userTokenHeader":{"type":"apiKey","name":"authorization","in":"header"}}}